peewee_sqlite_jsonfield/__init__.py
peewee_sqlite_jsonfield-0.1.0.dist-info/METADATA
peewee_sqlite_jsonfield-0.1.0.dist-info/WHEEL
peewee_sqlite_jsonfield-0.1.0.dist-info/RECORD
