Metadata-Version: 2.4
Name: peewee-sqlite-jsonfield
Version: 0.1.0
Summary: Super-charged JSON field for Peewee + SQLite JSON1
Author-email: Demiurge <megamen932@gmail.com>
License: MIT
Requires-Dist: peewee>=3.17
Provides-Extra: speed
Requires-Dist: orjson>=3.10; extra == 'speed'
Requires-Dist: ujson>=5.9; extra == 'speed'
